random_jokes/__init__.py
random_jokes/jokes.py
random_jokes-0.1.0.dist-info/entry_points.txt
random_jokes-0.1.0.dist-info/METADATA
random_jokes-0.1.0.dist-info/WHEEL
random_jokes-0.1.0.dist-info/RECORD
